{
  "stac_version": "1.1.0",
  "stac_extensions": [],
  "type": "Feature",
  "id": "20250328_185753_93_2514",
  "collection": "psscene",
  "properties": {
    "datetime": "2025-03-28T18:57:53.936226Z",
    "gsd": 3.8,
    "license": "CC-BY-4.0",
    "constellation": "PlanetScope",
    "created": "2025-03-29T04:40:51Z",
    "updated": "2025-03-29T09:59:38Z"
  },
  "bbox": [
    -112.20425531681443,
    57.270410635815075,
    -111.57459138311025,
    57.52717839502688
  ],
  "geometry": {
    "type": "Polygon",
    "coordinates": [
      [
        [
          -112.11229789158476,
          57.52717839502688
        ],
        [
          -112.20425531681443,
          57.35555678227024
        ],
        [
          -111.6695609399043,
          57.270410635815075
        ],
        [
          -111.57459138311025,
          57.44277170872108
        ],
        [
          -112.11229789158476,
          57.52717839502688
        ]
      ]
    ]
  },
  "assets": {
    "metadata": {
      "type": "application/json",
      "title": "JSON Metadata",
      "href": "https://storage.googleapis.com/open-cogs/planet-stac/open-canada/ft-mckay/psscene/20250328_185753_93_2514/20250328_185753_93_2514_metadata.json",
      "roles": [
        "metadata"
      ]
    },
    "sr": {
      "type": "image/tiff; application=geotiff; profile=cloud-optimized",
      "title": "Surface Reflectance",
      "href": "https://storage.googleapis.com/open-cogs/planet-stac/open-canada/ft-mckay/psscene/20250328_185753_93_2514/20250328_185753_93_2514_3B_AnalyticMS_SR_8b.tif",
      "roles": [
        "data",
        "reflectance"
      ]
    },
    "udm": {
      "type": "image/tiff; application=geotiff; profile=cloud-optimized",
      "title": "Usable Data Mask",
      "href": "https://storage.googleapis.com/open-cogs/planet-stac/open-canada/ft-mckay/psscene/20250328_185753_93_2514/20250328_185753_93_2514_3B_udm2.tif",
      "roles": [
        "data"
      ]
    },
    "xml-metadata": {
      "type": "application/xml",
      "title": "XML Metadata",
      "href": "https://storage.googleapis.com/open-cogs/planet-stac/open-canada/ft-mckay/psscene/20250328_185753_93_2514/20250328_185753_93_2514_3B_AnalyticMS_8b_metadata.xml",
      "roles": [
        "metadata"
      ]
    }
  },
  "links": [
    {
      "href": "../../../../catalog.json",
      "rel": "root",
      "type": "application/json"
    },
    {
      "href": "../collection.json",
      "rel": "collection",
      "title": "PlanetScope",
      "type": "application/json"
    },
    {
      "href": "../collection.json",
      "rel": "parent",
      "title": "PlanetScope",
      "type": "application/json"
    }
  ]
}