{
  "stac_version": "1.0.0",
  "stac_extensions": [
    "https://stac-extensions.github.io/eo/v1.1.0/schema.json",
    "https://stac-extensions.github.io/file/v2.0.0/schema.json",
    "https://stac-extensions.github.io/raster/v1.1.0/schema.json",
    "https://stac-extensions.github.io/projection/v1.1.0/schema.json",
    "https://stac-extensions.github.io/stereo-imagery/v1.0.0/schema.json",
    "https://stac-extensions.github.io/view/v1.0.0/schema.json",
    "https://planetlabs.github.io/stac-extension/v1.0.0-beta.3/schema.json"
  ],
  "type": "Feature",
  "id": "20210101_184738_ssc13_u0001",
  "collection": "san-francisco",
  "properties": {
    "datetime": "2021-01-01T18:47:38.75Z",
    "gsd": 0.72,
    "platform": "SSC13",
    "constellation": "skysat",
    "created": "2021-01-01T23:59:43Z",
    "eo:cloud_cover": 0,
    "eo:snow_cover": 0,
    "pl:clear_percent": 98,
    "pl:ground_control_ratio": 0.88,
    "pl:item_type": "SkySatCollect",
    "pl:pixel_resolution": 0.5,
    "pl:publishing_stage": "finalized",
    "pl:quality_category": "standard",
    "pl:strip_id": "s113_20210101T184738Z",
    "proj:epsg": 32610,
    "proj:shape": [
      40528,
      12771
    ],
    "proj:transform": [
      0.5,
      0,
      544780.5,
      0,
      -0.5,
      4196162.5,
      0,
      0,
      1
    ],
    "providers": [
      {
        "description": "Contact Planet at [planet.com/contact-sales](https://www.planet.com/contact-sales/)",
        "name": "Planet Labs PBC",
        "roles": [
          "producer",
          "processor"
        ],
        "url": "https://www.planet.com"
      }
    ],
    "stereo-img:count": 2,
    "stereo-img:group": "20210101_184738_ssc13",
    "stereo-img:number": 1,
    "updated": "2021-01-01T23:59:43Z",
    "view:azimuth": 352,
    "view:off_nadir": 16.7,
    "view:sun_azimuth": 158,
    "view:sun_elevation": 26
  },
  "bbox": [
    -122.49081839008039,
    37.72893228818372,
    -122.41851802302043,
    37.91179404951477
  ],
  "geometry": {
    "type": "Polygon",
    "coordinates": [
      [
        [
          -122.41947322562886,
          37.737906907270634
        ],
        [
          -122.41945906115042,
          37.73790647307181
        ],
        [
          -122.41955326133403,
          37.72893228818372
        ],
        [
          -122.44523357671763,
          37.729439314249575
        ],
        [
          -122.44521324796173,
          37.7372418081035
        ],
        [
          -122.44525166284893,
          37.737242876176815
        ],
        [
          -122.44517136237724,
          37.74483457011582
        ],
        [
          -122.4452175774176,
          37.744836021712494
        ],
        [
          -122.44515388825657,
          37.752529830776524
        ],
        [
          -122.44520944814383,
          37.75253192968528
        ],
        [
          -122.44514034882756,
          37.75662031546723
        ],
        [
          -122.46478697240617,
          37.75698973717797
        ],
        [
          -122.46483758505293,
          37.75357275110146
        ],
        [
          -122.46477555791483,
          37.753572110644235
        ],
        [
          -122.46485144328561,
          37.746008859261835
        ],
        [
          -122.46480148809225,
          37.74600845730492
        ],
        [
          -122.46485668331728,
          37.73830900942944
        ],
        [
          -122.4647943977827,
          37.73830843296373
        ],
        [
          -122.4648813171461,
          37.72934343549417
        ],
        [
          -122.49045339642286,
          37.729596515978386
        ],
        [
          -122.49037197485153,
          37.73714912042021
        ],
        [
          -122.4904526564188,
          37.73714980783035
        ],
        [
          -122.49038763639614,
          37.74483861731237
        ],
        [
          -122.49048027422916,
          37.744839531862745
        ],
        [
          -122.4904045199876,
          37.75245823334035
        ],
        [
          -122.4904919446523,
          37.75245901997948
        ],
        [
          -122.49040600784544,
          37.760033742777885
        ],
        [
          -122.49049682501246,
          37.76003506806203
        ],
        [
          -122.49039962452531,
          37.767542215847456
        ],
        [
          -122.49048854559139,
          37.76754357370948
        ],
        [
          -122.49041823404268,
          37.775164671331865
        ],
        [
          -122.49049936648586,
          37.77516605839093
        ],
        [
          -122.4904016668942,
          37.78270320658893
        ],
        [
          -122.4904687278399,
          37.78270433966706
        ],
        [
          -122.49035442601586,
          37.79012414024501
        ],
        [
          -122.49041923591331,
          37.790124807997124
        ],
        [
          -122.49031676027872,
          37.797679159019864
        ],
        [
          -122.4904177160197,
          37.797679934657204
        ],
        [
          -122.49032439754632,
          37.805232642388596
        ],
        [
          -122.49041309256319,
          37.8052340613153
        ],
        [
          -122.49033329777252,
          37.812781466869765
        ],
        [
          -122.49041243722753,
          37.812782753753694
        ],
        [
          -122.4903429361681,
          37.82034264174988
        ],
        [
          -122.49042260368888,
          37.82034392784882
        ],
        [
          -122.49035592981967,
          37.82795525090455
        ],
        [
          -122.49047048358162,
          37.82795719027624
        ],
        [
          -122.49046693299641,
          37.83624355262251
        ],
        [
          -122.49060625012723,
          37.83624981658274
        ],
        [
          -122.49050762668155,
          37.843560398787865
        ],
        [
          -122.49063618394742,
          37.8435648975338
        ],
        [
          -122.49054333082104,
          37.851717388149474
        ],
        [
          -122.49070246877135,
          37.85172335120067
        ],
        [
          -122.49057344322637,
          37.85937474107176
        ],
        [
          -122.49074121397805,
          37.85937813652397
        ],
        [
          -122.49064591601434,
          37.86733635607912
        ],
        [
          -122.49072102250497,
          37.867337119758886
        ],
        [
          -122.49064014202722,
          37.87493602252353
        ],
        [
          -122.49081839008039,
          37.87493839402404
        ],
        [
          -122.49069936931707,
          37.88415966264889
        ],
        [
          -122.4674211224772,
          37.8839660986358
        ],
        [
          -122.46739770027455,
          37.887565106733405
        ],
        [
          -122.46752935731766,
          37.887568324455096
        ],
        [
          -122.46743255592125,
          37.895677709205046
        ],
        [
          -122.46758829175361,
          37.89568093814113
        ],
        [
          -122.46752629215125,
          37.90316335171044
        ],
        [
          -122.46765116442509,
          37.90316596170138
        ],
        [
          -122.46757201588458,
          37.91179404951477
        ],
        [
          -122.4438283099271,
          37.911167622520054
        ],
        [
          -122.44286003915572,
          37.9043550795433
        ],
        [
          -122.44139752809632,
          37.90433330416464
        ],
        [
          -122.44147199383133,
          37.89607782493726
        ],
        [
          -122.44135324834613,
          37.896075598410185
        ],
        [
          -122.4414289163192,
          37.88791806974644
        ],
        [
          -122.44134472032754,
          37.88791581238821
        ],
        [
          -122.44137578217016,
          37.884209944856515
        ],
        [
          -122.41859841435793,
          37.88363293780392
        ],
        [
          -122.41866213363392,
          37.875991741218165
        ],
        [
          -122.41855779221025,
          37.87598951896473
        ],
        [
          -122.41864219659263,
          37.867824068791826
        ],
        [
          -122.41856042048262,
          37.86782252382709
        ],
        [
          -122.41864310983144,
          37.85970262582984
        ],
        [
          -122.41856650693781,
          37.85970117785201
        ],
        [
          -122.41862763324683,
          37.85162898511654
        ],
        [
          -122.41860285639531,
          37.85162854714841
        ],
        [
          -122.4186994804805,
          37.84244748358665
        ],
        [
          -122.44138349454036,
          37.84285119472729
        ],
        [
          -122.44138944104937,
          37.84213016098734
        ],
        [
          -122.41878984472461,
          37.841717235383705
        ],
        [
          -122.41868147085574,
          37.836706155800854
        ],
        [
          -122.41851802302043,
          37.836703416293254
        ],
        [
          -122.41863199864925,
          37.82886425958491
        ],
        [
          -122.41857710513712,
          37.828863332123994
        ],
        [
          -122.41872715925611,
          37.819647871404676
        ],
        [
          -122.41875722929645,
          37.819648445065646
        ],
        [
          -122.4188093293971,
          37.813644597350375
        ],
        [
          -122.41878448375,
          37.813644133884225
        ],
        [
          -122.41886963682657,
          37.80609746077196
        ],
        [
          -122.41884133764097,
          37.80609695884466
        ],
        [
          -122.41894165726664,
          37.798683780239315
        ],
        [
          -122.4189414616405,
          37.798683777792824
        ],
        [
          -122.41900466400726,
          37.79104478838658
        ],
        [
          -122.41900002271018,
          37.79104467882948
        ],
        [
          -122.41906129124804,
          37.78336888205614
        ],
        [
          -122.41905337692283,
          37.78336870076302
        ],
        [
          -122.41912782802736,
          37.77573198925734
        ],
        [
          -122.41910739442973,
          37.77573148397623
        ],
        [
          -122.41918778988449,
          37.76809832073977
        ],
        [
          -122.41916285195279,
          37.76809760387411
        ],
        [
          -122.41925419785329,
          37.76050509696638
        ],
        [
          -122.41922871108012,
          37.76050430265231
        ],
        [
          -122.41932282474731,
          37.75292648579436
        ],
        [
          -122.41929870941689,
          37.75292556271628
        ],
        [
          -122.41939828443613,
          37.745340011747025
        ],
        [
          -122.41935868296815,
          37.74533865544095
        ],
        [
          -122.41947322562886,
          37.737906907270634
        ]
      ]
    ]
  },
  "assets": {
    "all-frames": {
      "type": "application/zip",
      "title": "L1A All-Frames",
      "href": "https://storage.googleapis.com/open-cogs/planet-stac/san-francisco-usa/20210101_184738_ssc13_u0001/20210101_184738_ssc13_u0001_l1a_frames_archive.zip",
      "file:size": 3541856193,
      "roles": [
        "data",
        "archive"
      ]
    },
    "analytic:ortho_analytic": {
      "type": "image/tiff; application=geotiff; profile=cloud-optimized",
      "href": "https://storage.googleapis.com/open-cogs/planet-stac/san-francisco-usa/20210101_184738_ssc13_u0001/20210101_184738_ssc13_u0001_analytic_file_format.tif",
      "eo:bands": [
        {
          "center_wavelength": 470,
          "common_name": "blue",
          "full_width_half_max": 70,
          "name": "BLUE"
        },
        {
          "center_wavelength": 560,
          "common_name": "green",
          "full_width_half_max": 80,
          "name": "GREEN"
        },
        {
          "center_wavelength": 645,
          "common_name": "red",
          "full_width_half_max": 90,
          "name": "RED"
        },
        {
          "center_wavelength": 800,
          "common_name": "nir",
          "full_width_half_max": 152,
          "name": "NIR"
        }
      ],
      "raster:bands": [
        {
          "data_type": "uint16",
          "histogram": {
            "buckets": [
              63753,
              188485,
              14521,
              1529,
              349,
              89,
              55,
              52,
              30,
              13
            ],
            "count": 11,
            "max": 10242,
            "min": 2751
          },
          "nodata": 0,
          "offset": 0,
          "sampling": "area",
          "scale": 1,
          "statistics": {
            "maximum": 10242,
            "mean": 3761.4343340424584,
            "minimum": 2751,
            "stddev": 400.9935422697009,
            "valid_percent": 81.29232778637771
          }
        },
        {
          "data_type": "uint16",
          "histogram": {
            "buckets": [
              70171,
              186155,
              10297,
              1600,
              386,
              108,
              57,
              56,
              32,
              14
            ],
            "count": 11,
            "max": 9159,
            "min": 1776
          },
          "nodata": 0,
          "offset": 0,
          "sampling": "area",
          "scale": 1,
          "statistics": {
            "maximum": 9159,
            "mean": 2719.6955697049943,
            "minimum": 1776,
            "stddev": 381.151023507504,
            "valid_percent": 81.29232778637771
          }
        },
        {
          "data_type": "uint16",
          "histogram": {
            "buckets": [
              155039,
              101554,
              10012,
              1589,
              401,
              128,
              62,
              51,
              30,
              10
            ],
            "count": 11,
            "max": 7791,
            "min": 1079
          },
          "nodata": 0,
          "offset": 0,
          "sampling": "area",
          "scale": 1,
          "statistics": {
            "maximum": 7791,
            "mean": 1761.8012503905145,
            "minimum": 1079,
            "stddev": 348.7603626635925,
            "valid_percent": 81.29232778637771
          }
        },
        {
          "data_type": "uint16",
          "histogram": {
            "buckets": [
              133390,
              77105,
              43061,
              11177,
              2727,
              1061,
              268,
              58,
              25,
              4
            ],
            "count": 11,
            "max": 5975,
            "min": 656
          },
          "nodata": 0,
          "offset": 0,
          "sampling": "area",
          "scale": 1,
          "statistics": {
            "maximum": 5975,
            "mean": 1353.2123729897796,
            "minimum": 656,
            "stddev": 509.2693508769724,
            "valid_percent": 81.29232778637771
          }
        }
      ],
      "roles": [
        "data"
      ]
    },
    "analytic:ortho_analytic_udm": {
      "type": "image/tiff; application=geotiff; profile=cloud-optimized",
      "href": "https://storage.googleapis.com/open-cogs/planet-stac/san-francisco-usa/20210101_184738_ssc13_u0001/20210101_184738_ssc13_u0001_analytic_udm.tif",
      "roles": [
        "metadata",
        "snow-ice",
        "cloud",
        "cloud-shadow"
      ]
    },
    "metadata": {
      "type": "application/json",
      "href": "https://storage.googleapis.com/open-cogs/planet-stac/san-francisco-usa/20210101_184738_ssc13_u0001/20210101_184738_ssc13_u0001_metadata.json",
      "roles": [
        "metadata"
      ]
    },
    "visual:ortho_visual": {
      "type": "image/tiff; application=geotiff; profile=cloud-optimized",
      "href": "https://storage.googleapis.com/open-cogs/planet-stac/san-francisco-usa/20210101_184738_ssc13_u0001/20210101_184738_ssc13_u0001_visual.tif",
      "eo:bands": [
        {
          "center_wavelength": 645,
          "common_name": "red",
          "full_width_half_max": 90,
          "name": "RED"
        },
        {
          "center_wavelength": 560,
          "common_name": "green",
          "full_width_half_max": 80,
          "name": "GREEN"
        },
        {
          "center_wavelength": 470,
          "common_name": "blue",
          "full_width_half_max": 70,
          "name": "BLUE"
        }
      ],
      "roles": [
        "data",
        "visual"
      ]
    }
  },
  "links": [
    {
      "href": "https://assets.planet.com/docs/Planet_Basic_L1A_All-Frames_User_Guide.pdf",
      "rel": "about",
      "title": "Documentation for Planet L1A All-Frames Assets",
      "type": "application/pdf"
    },
    {
      "href": "../../../catalog.json",
      "rel": "root",
      "type": "application/json"
    },
    {
      "href": "https://api.planet.com/data/v1/item-types/SkySatCollect/items/20210101_184738_ssc13_u0001",
      "rel": "via"
    },
    {
      "href": "../catalog.json",
      "rel": "collection",
      "title": "San Francisco, California, United States",
      "type": "application/json"
    },
    {
      "href": "../stereo.json",
      "rel": "parent",
      "type": "application/json"
    },
    {
      "href": "../20210101_184738_ssc13_u0002/20210101_184738_ssc13_u0002.json",
      "rel": "related",
      "stereo-img:number": 2,
      "type": "application/json"
    },
    {
      "href": "./20210101_184738_ssc13_u0001.json",
      "rel": "self",
      "type": "application/json"
    }
  ]
}