{
  "stac_version": "1.0.0",
  "stac_extensions": [
    "https://stac-extensions.github.io/eo/v1.0.0/schema.json",
    "https://stac-extensions.github.io/view/v1.0.0/schema.json",
    "https://stac-extensions.github.io/projection/v1.0.0/schema.json"
  ],
  "type": "Feature",
  "id": "20201213_083452_ssc1_u0001",
  "collection": "planet-stac-skysat",
  "properties": {
    "title": "Kampala, Uganda",
    "datetime": "2020-12-13T08:34:52.312Z",
    "gsd": 0.66,
    "platform": "SSC1",
    "constellation": "skysat",
    "created": "2020-12-13T13:08:25Z",
    "eo:cloud_cover": 7.000000000000001,
    "pl:clear_percent": 72,
    "pl:item_type": "SkySatCollect",
    "pl:pixel_resolution": 0.5,
    "pl:publishing_stage": "finalized",
    "pl:quality_category": "standard",
    "pl:strip_id": "s3_20201213T083452Z",
    "proj:epsg": 32636,
    "proj:shape": [
      40585,
      11836
    ],
    "proj:transform": [
      0.5,
      0,
      450611,
      0,
      -0.5,
      50059.5,
      0,
      0,
      1
    ],
    "providers": [
      {
        "description": "Contact Planet at [planet.com/contact-sales](https://www.planet.com/contact-sales/)",
        "name": "Planet",
        "roles": [
          "producer",
          "processor"
        ],
        "url": "https://www.planet.com"
      }
    ],
    "updated": "2020-12-13T13:08:25Z",
    "view:azimuth": 286.5,
    "view:off_nadir": 8.3,
    "view:sun_azimuth": 145.6,
    "view:sun_elevation": 61.1
  },
  "bbox": [
    32.55615198410779,
    0.2693073386275247,
    32.6093300736682,
    0.45288824379086157
  ],
  "geometry": {
    "type": "Polygon",
    "coordinates": [
      [
        [
          32.57545127581085,
          0.27731994221403544
        ],
        [
          32.57558335444891,
          0.2773176992799415
        ],
        [
          32.57536931510849,
          0.2693073386275247
        ],
        [
          32.55635452552247,
          0.26964006578049016
        ],
        [
          32.5564746153844,
          0.27647901509714967
        ],
        [
          32.5563545011919,
          0.2764812014175362
        ],
        [
          32.556428989424305,
          0.28335666063254517
        ],
        [
          32.5563470495743,
          0.2833582264533602
        ],
        [
          32.55651127493574,
          0.2902152624138939
        ],
        [
          32.556428216098055,
          0.2902169188821614
        ],
        [
          32.556523861686536,
          0.29700191465787495
        ],
        [
          32.5563850008274,
          0.29700480280198943
        ],
        [
          32.55650941205312,
          0.3038078312076643
        ],
        [
          32.55639579286516,
          0.303810264922788
        ],
        [
          32.55650355676513,
          0.31064048319536286
        ],
        [
          32.556430669510796,
          0.31064209888648336
        ],
        [
          32.55655791022629,
          0.31749505298410385
        ],
        [
          32.5565147091174,
          0.31749601578482645
        ],
        [
          32.5566689407136,
          0.3243268883319511
        ],
        [
          32.556596710470245,
          0.32432849543823367
        ],
        [
          32.55672409938422,
          0.33105320633149005
        ],
        [
          32.556513797277034,
          0.33105801179938266
        ],
        [
          32.556660626580474,
          0.3377320076012593
        ],
        [
          32.55639614741135,
          0.3377381480948203
        ],
        [
          32.5565533131597,
          0.3444343659515808
        ],
        [
          32.556319310518795,
          0.3444397806664865
        ],
        [
          32.55643795186329,
          0.35117758081378364
        ],
        [
          32.556245927135606,
          0.35118223791627456
        ],
        [
          32.55632673286699,
          0.35797579751306463
        ],
        [
          32.55615198410779,
          0.3579802394972172
        ],
        [
          32.55629799129844,
          0.3647973801914043
        ],
        [
          32.55618405072512,
          0.36480034362522856
        ],
        [
          32.55632829477409,
          0.37166785256396195
        ],
        [
          32.55627226717389,
          0.371669322602552
        ],
        [
          32.55636544583224,
          0.37860739541774835
        ],
        [
          32.55634984942914,
          0.37860781691753426
        ],
        [
          32.55654681524774,
          0.3865959800336174
        ],
        [
          32.55658483383815,
          0.38659504252686644
        ],
        [
          32.556723703116226,
          0.39356963760570834
        ],
        [
          32.55682283856389,
          0.39356713104779384
        ],
        [
          32.55696129547236,
          0.40058558766402164
        ],
        [
          32.556971133094585,
          0.40058532137520453
        ],
        [
          32.55707674221838,
          0.406268704596653
        ],
        [
          32.55692497510335,
          0.40627284090463756
        ],
        [
          32.55703824565999,
          0.4133328201520374
        ],
        [
          32.556698315259595,
          0.4133424088134222
        ],
        [
          32.55683544400364,
          0.4203675612259352
        ],
        [
          32.55649570077403,
          0.4203767629072455
        ],
        [
          32.55664392392827,
          0.4284120537587152
        ],
        [
          32.573766994219625,
          0.4279205400881998
        ],
        [
          32.57381217606591,
          0.4307839843073558
        ],
        [
          32.57368483182909,
          0.43078723151815534
        ],
        [
          32.573805457013385,
          0.4377924317969467
        ],
        [
          32.57348989829377,
          0.4378003191310816
        ],
        [
          32.573592336198764,
          0.4448624748186288
        ],
        [
          32.573268864831455,
          0.44487098253143836
        ],
        [
          32.57340798296232,
          0.45288824379086157
        ],
        [
          32.592532484841655,
          0.4523882185654847
        ],
        [
          32.59240195398406,
          0.4453548744178447
        ],
        [
          32.59273240518151,
          0.4453467787337945
        ],
        [
          32.592596227280254,
          0.4382814392574385
        ],
        [
          32.59290344093438,
          0.4382737726869994
        ],
        [
          32.59278014243946,
          0.43154399004106525
        ],
        [
          32.592903910673606,
          0.4315409537497169
        ],
        [
          32.5928451537938,
          0.42816801163855234
        ],
        [
          32.60888144784569,
          0.42769016865412907
        ],
        [
          32.60876220873251,
          0.42067815497479305
        ],
        [
          32.6090803665796,
          0.4206684451201022
        ],
        [
          32.608953071566646,
          0.41364515930116746
        ],
        [
          32.60927394808096,
          0.41363628790496143
        ],
        [
          32.60918990748183,
          0.4068837983468199
        ],
        [
          32.6093300736682,
          0.40688003706955894
        ],
        [
          32.6091724374956,
          0.3988784518562705
        ],
        [
          32.609136214901696,
          0.3988793820852739
        ],
        [
          32.60899653808138,
          0.3919898486822849
        ],
        [
          32.60890096583407,
          0.39199216201425563
        ],
        [
          32.60882479933149,
          0.3849801109693398
        ],
        [
          32.60875999441957,
          0.3849817760238451
        ],
        [
          32.60862592335673,
          0.3791660100775469
        ],
        [
          32.60862982276387,
          0.37916591870061556
        ],
        [
          32.608611235699385,
          0.3785288854390824
        ],
        [
          32.60860018368392,
          0.37804946852531246
        ],
        [
          32.608597249496846,
          0.37804953722219703
        ],
        [
          32.60843075012931,
          0.3723431151437437
        ],
        [
          32.60847532050478,
          0.372342167732489
        ],
        [
          32.60845364906133,
          0.3655150787293176
        ],
        [
          32.60857507530486,
          0.3655123148926414
        ],
        [
          32.6084503642889,
          0.35876520721073657
        ],
        [
          32.608604157518634,
          0.3587619656305854
        ],
        [
          32.608467083157805,
          0.3520528941246339
        ],
        [
          32.60865128552795,
          0.35204915700307543
        ],
        [
          32.60852429231229,
          0.34536984430000933
        ],
        [
          32.60875340997931,
          0.3453652815776294
        ],
        [
          32.60866248990382,
          0.33871170289149616
        ],
        [
          32.60891919546109,
          0.3387065445004592
        ],
        [
          32.6088624778372,
          0.3320025329045035
        ],
        [
          32.60905567749803,
          0.33199868924107573
        ],
        [
          32.60898521380772,
          0.32518356636385615
        ],
        [
          32.60905995026392,
          0.32518214569466186
        ],
        [
          32.608957626881626,
          0.3183541081018135
        ],
        [
          32.609004380992175,
          0.31835325502259626
        ],
        [
          32.60886553590469,
          0.3115564528604969
        ],
        [
          32.60895281901476,
          0.31155491723473927
        ],
        [
          32.60879066694545,
          0.30478511525579177
        ],
        [
          32.60889294814989,
          0.30478337896630125
        ],
        [
          32.608749804034595,
          0.2980312281413751
        ],
        [
          32.60889333004571,
          0.29802883083041964
        ],
        [
          32.60878505819571,
          0.29120727730081297
        ],
        [
          32.60885315405623,
          0.2912061949966898
        ],
        [
          32.608808478745715,
          0.28436334599912577
        ],
        [
          32.60889749149367,
          0.28436193983396796
        ],
        [
          32.60881077256566,
          0.27755512900393237
        ],
        [
          32.60893146117394,
          0.2775532880731404
        ],
        [
          32.6087114002564,
          0.269543457348037
        ],
        [
          32.58960743158738,
          0.26984423699930377
        ],
        [
          32.589607165072906,
          0.2766541185030774
        ],
        [
          32.589471747914004,
          0.27665629542538145
        ],
        [
          32.589689965941005,
          0.28349660893077583
        ],
        [
          32.58962889061435,
          0.2834976094792251
        ],
        [
          32.589780036912465,
          0.29032377298099865
        ],
        [
          32.589707176852514,
          0.29032496825963855
        ],
        [
          32.58972740623496,
          0.2940117985045227
        ],
        [
          32.57559339134502,
          0.29422894322711896
        ],
        [
          32.575520293502166,
          0.2910071583865199
        ],
        [
          32.57560244163686,
          0.29100558704438634
        ],
        [
          32.57550524650943,
          0.28414927488071506
        ],
        [
          32.575579438431504,
          0.2841479296217091
        ],
        [
          32.57545127581085,
          0.27731994221403544
        ]
      ]
    ]
  },
  "assets": {
    "analytic_sr_udm2:ortho_analytic_sr": {
      "type": "image/tiff; application=geotiff; profile=cloud-optimized",
      "href": "https://storage.googleapis.com/open-cogs/planet-stac/20201213_083452_ssc1_u0001/20201213_083452_ssc1_u0001_analytic_SR_file_format.tif",
      "eo:bands": [
        {
          "center_wavelength": 470,
          "common_name": "blue",
          "full_width_half_max": 70,
          "name": "BLUE"
        },
        {
          "center_wavelength": 560,
          "common_name": "green",
          "full_width_half_max": 80,
          "name": "GREEN"
        },
        {
          "center_wavelength": 645,
          "common_name": "red",
          "full_width_half_max": 90,
          "name": "RED"
        },
        {
          "center_wavelength": 800,
          "common_name": "nir",
          "full_width_half_max": 152,
          "name": "NIR"
        }
      ],
      "roles": [
        "data",
        "reflectance"
      ]
    },
    "analytic_sr_udm2:ortho_analytic_udm2": {
      "type": "image/tiff; application=geotiff; profile=cloud-optimized",
      "href": "https://storage.googleapis.com/open-cogs/planet-stac/20201213_083452_ssc1_u0001/20201213_083452_ssc1_u0001_udm2.tif",
      "roles": [
        "metadata",
        "snow-ice",
        "cloud",
        "cloud-shadow"
      ]
    },
    "metadata": {
      "type": "application/json",
      "href": "https://storage.googleapis.com/open-cogs/planet-stac/20201213_083452_ssc1_u0001/20201213_083452_ssc1_u0001_metadata.json",
      "roles": [
        "metadata"
      ]
    },
    "thumbnail": {
      "type": "image/png",
      "href": "https://storage.googleapis.com/open-cogs/planet-stac/20201213_083452_ssc1_u0001/20201213_083452_ssc1_u0001_visual_file_format.thumbnail.png",
      "roles": [
        "thumbnail"
      ]
    },
    "visual:ortho_visual": {
      "type": "image/tiff; application=geotiff; profile=cloud-optimized",
      "href": "https://storage.googleapis.com/open-cogs/planet-stac/20201213_083452_ssc1_u0001/20201213_083452_ssc1_u0001_visual_file_format.tif",
      "eo:bands": [
        {
          "center_wavelength": 645,
          "common_name": "red",
          "full_width_half_max": 90,
          "name": "RED"
        },
        {
          "center_wavelength": 560,
          "common_name": "green",
          "full_width_half_max": 80,
          "name": "GREEN"
        },
        {
          "center_wavelength": 470,
          "common_name": "blue",
          "full_width_half_max": 70,
          "name": "BLUE"
        }
      ],
      "roles": [
        "data",
        "visual"
      ]
    }
  },
  "links": [
    {
      "href": "https://api.planet.com/data/v1/item-types/SkySatCollect/items/20201213_083452_ssc1_u0001",
      "rel": "via"
    },
    {
      "href": "../../catalog.json",
      "rel": "root",
      "type": "application/json"
    },
    {
      "href": "../collection.json",
      "rel": "collection",
      "type": "application/json"
    },
    {
      "href": "../collection.json",
      "rel": "parent",
      "type": "application/json"
    },
    {
      "href": "./20201213_083452_ssc1_u0001.json",
      "rel": "self",
      "type": "application/json"
    }
  ]
}